streamspeech/__init__.py
streamspeech/__main__.py
streamspeech/app.py
streamspeech/app_main.py
streamspeech/version.py
streamspeech-2023.12.6.dist-info/LICENSE
streamspeech-2023.12.6.dist-info/METADATA
streamspeech-2023.12.6.dist-info/WHEEL
streamspeech-2023.12.6.dist-info/top_level.txt
streamspeech-2023.12.6.dist-info/RECORD
