Metadata-Version: 2.1
Name: streamspeech
Version: 2023.12.6
Summary: Text to Speech with Generative AI
Home-page: http://www.github.com/Nelson-Gon/streamspeech
Download-URL: https://github.com/Nelson-Gon/streamspeech/archive/refs/tags/v2023.12.06.zip
Author: Nelson Gonzabato
Author-email: gonzabato@hotmail.com
License: MIT
Keywords: generative-ai speechbrain tts text-to-speech gan artificial-intelligence ai
Requires-Python: >=3.9
License-File: LICENSE
Requires-Dist: streamlit ==1.29.0
Requires-Dist: speechbrain ==0.5.16
Requires-Dist: google-ai-generativelanguage ==0.3.3
Requires-Dist: google-api-core ==2.14.0
Requires-Dist: google-auth ==2.24.0
Requires-Dist: google-auth-oauthlib ==1.1.0
Requires-Dist: google-generativeai ==0.2.2
Requires-Dist: googleapis-common-protos ==1.61.0
Requires-Dist: shiny ==0.6.0
Requires-Dist: shinyswatch ==0.4.1
Requires-Dist: shinywidgets ==0.2.4
Requires-Dist: joblib ==1.3.2
